jupyter_linkedin/__init__.py
jupyter_linkedin/_version.py
jupyter_linkedin/handlers.py
jupyter_linkedin/tests/__init__.py
jupyter_linkedin/tests/test_handlers.py
jupyter_linkedin-0.0.2.data/data/etc/jupyter/jupyter_notebook_config.d/jupyter_linkedin.json
jupyter_linkedin-0.0.2.data/data/etc/jupyter/jupyter_server_config.d/jupyter_linkedin.json
jupyter_linkedin-0.0.2.data/data/share/jupyter/labextensions/@datalayer/jupyter-linkedin/build_log.json
jupyter_linkedin-0.0.2.data/data/share/jupyter/labextensions/@datalayer/jupyter-linkedin/package.json
jupyter_linkedin-0.0.2.data/data/share/jupyter/labextensions/@datalayer/jupyter-linkedin/schemas/@datalayer/jupyter-linkedin/package.json.orig
jupyter_linkedin-0.0.2.data/data/share/jupyter/labextensions/@datalayer/jupyter-linkedin/schemas/@datalayer/jupyter-linkedin/plugin.json
jupyter_linkedin-0.0.2.data/data/share/jupyter/labextensions/@datalayer/jupyter-linkedin/static/design_icons_lib_index_js.cf6f023299c388230c7a.js
jupyter_linkedin-0.0.2.data/data/share/jupyter/labextensions/@datalayer/jupyter-linkedin/static/design_icons_lib_index_js.cf6f023299c388230c7a.js.map
jupyter_linkedin-0.0.2.data/data/share/jupyter/labextensions/@datalayer/jupyter-linkedin/static/lib_index_js.ad95365cfc148d8e378a.js
jupyter_linkedin-0.0.2.data/data/share/jupyter/labextensions/@datalayer/jupyter-linkedin/static/lib_index_js.ad95365cfc148d8e378a.js.map
jupyter_linkedin-0.0.2.data/data/share/jupyter/labextensions/@datalayer/jupyter-linkedin/static/remoteEntry.867c8af09b9e39ddaf08.js
jupyter_linkedin-0.0.2.data/data/share/jupyter/labextensions/@datalayer/jupyter-linkedin/static/remoteEntry.867c8af09b9e39ddaf08.js.map
jupyter_linkedin-0.0.2.data/data/share/jupyter/labextensions/@datalayer/jupyter-linkedin/static/style.js
jupyter_linkedin-0.0.2.data/data/share/jupyter/labextensions/@datalayer/jupyter-linkedin/static/style_index_js.a760208d8f3426807152.js
jupyter_linkedin-0.0.2.dist-info/METADATA
jupyter_linkedin-0.0.2.dist-info/WHEEL
jupyter_linkedin-0.0.2.dist-info/licenses/LICENSE
jupyter_linkedin-0.0.2.dist-info/RECORD
